{
  "version": 2.12,
  "cardset_id": "17555ac4-218b-4118-85e7-2f77ea954175",
  "name": "Heroes",
  "blueprint_id": "53f91afb-ec6d-4beb-8a56-19635b37ef61",
  "hint_order_index": 1,
  "cards": [
    {
      "card_id": "5f0d0568-65bc-4f8e-9250-d33ff8f924e4",
      "amount": 1,
      "front_layers": [
        {
          "blueprint_layer_id": "82588eae-b753-42a6-b723-200e1aebce76",
          "panels": [
            {
              "blueprint_panel_id": "655eb452-7f0a-46cd-9f92-50031ba1486a",
              "rotation": 0,
              "type": "icon",
              "data": {
                "uri": "Other/concentration-orb",
                "color_tint": "#FFFFFFFF",
                "color_background": "#00000000"
              }
            }
          ]
        },
        {
          "blueprint_layer_id": "fd780760-2006-4822-aac5-c6b3e1a23511",
          "panels": [
            {
              "blueprint_panel_id": "8f334754-feb9-4f34-b2a9-f4092ee70b24",
              "rotation": 0,
              "type": "text",
              "data": {
                "text": "Weapon:"
              }
            },
            {
              "blueprint_panel_id": "42ba2cce-da7d-4e9e-acca-b1c8bfe55eec",
              "rotation": 0,
              "type": "text",
              "data": {
                "text": "{Body&Actions/punch}None"
              }
            },
            {
              "blueprint_panel_id": "60f160b7-c538-4fe8-9143-db7f1c33babc",
              "rotation": 0,
              "type": "text",
              "data": {
                "text": "<b>Election:</b> If you have 3 or more orange heroes on the field {Basic/st3_playback_play} you can turn 2/3 of your <b>mana</b> into <b>orange mana</b> for one turn."
              }
            },
            {
              "blueprint_panel_id": "92384782-2757-4eeb-ac1a-94f54aea0cad",
              "rotation": 0,
              "type": "text",
              "data": {
                "text": "Authority/HUN"
              }
            },
            {
              "blueprint_panel_id": "cff4dfa2-2de8-4320-b0b1-224e85db59db",
              "rotation": 0,
              "type": "text",
              "data": {
                "text": "25"
              }
            },
            {
              "blueprint_panel_id": "7f0d98a6-7eaf-40e4-a5a1-fcd174e78941",
              "rotation": 0,
              "type": "text",
              "data": {
                "text": "15"
              }
            },
            {
              "blueprint_panel_id": "ee7f97aa-6f6c-4eea-90c9-c0263053a61c",
              "rotation": 0,
              "type": "text",
              "data": {
                "text": "55          "
              }
            },
            {
              "blueprint_panel_id": "df446f32-d134-4afa-ae86-5d307f9fab6d",
              "rotation": 0,
              "type": "image",
              "data": {
                "uri": "%PROJECT%/Orbi.png",
                "zoom": 1.0,
                "offset": "0.004061399, -0.1515893"
              }
            },
            {
              "blueprint_panel_id": "24205eff-c76a-4f64-b312-a2a9262be6e5",
              "rotation": 0,
              "padding": "0, 0, 0, 0",
              "type": "text",
              "data": {
                "text": "{Abstract/plain-circle} 4",
                "color": "#FF8200FF",
                "outline_length": 1.0,
                "image_offset": "0, 0"
              }
            },
            {
              "blueprint_panel_id": "f81609a7-abac-42dc-bcb4-48ac8d0e1516",
              "rotation": 0,
              "type": "text",
              "data": {
                "text": "\n"
              }
            },
            {
              "blueprint_panel_id": "693b769c-1e06-4eba-ab1f-f972d2473746",
              "rotation": 0,
              "type": "text",
              "data": {
                "text": "\n"
              }
            },
            {
              "blueprint_panel_id": "6a7144d4-6d17-4957-a633-c8b17b11146d",
              "rotation": 0,
              "type": "text",
              "data": {
                "text": "\n"
              }
            },
            {
              "blueprint_panel_id": "ae20974a-89fb-4b5a-976d-8fe94f1f240d",
              "rotation": 0,
              "type": "text",
              "data": {
                "text": "\n"
              }
            },
            {
              "blueprint_panel_id": "1a958a14-339a-4740-b783-a4a2e494fc2a",
              "rotation": 0,
              "type": "text",
              "data": {
                "text": "Victor"
              }
            }
          ]
        }
      ]
    },
    {
      "card_id": "14619c74-8eb4-4829-b71d-51ff7bc98c2e",
      "amount": 1,
      "front_layers": [
        {
          "blueprint_layer_id": "82588eae-b753-42a6-b723-200e1aebce76",
          "panels": [
            {
              "blueprint_panel_id": "655eb452-7f0a-46cd-9f92-50031ba1486a",
              "rotation": 0,
              "type": "icon",
              "data": {
                "uri": "Other/concentration-orb",
                "color_tint": "#FFFFFFFF",
                "color_background": "#00000000"
              }
            }
          ]
        },
        {
          "blueprint_layer_id": "fd780760-2006-4822-aac5-c6b3e1a23511",
          "panels": [
            {
              "blueprint_panel_id": "8f334754-feb9-4f34-b2a9-f4092ee70b24",
              "rotation": 0,
              "type": "text",
              "data": {
                "text": "Weapon:"
              }
            },
            {
              "blueprint_panel_id": "42ba2cce-da7d-4e9e-acca-b1c8bfe55eec",
              "rotation": 0,
              "type": "text",
              "data": {
                "text": "{Body&Actions/punch}None"
              }
            },
            {
              "blueprint_panel_id": "60f160b7-c538-4fe8-9143-db7f1c33babc",
              "rotation": 0,
              "type": "text",
              "data": {
                "text": "<b>Money laundering:</b> In the strategy phase {Basic/st3_playback_play} You can ignore the <b>Orange Hero</b> cost on a Vehicle. Once per turn."
              }
            },
            {
              "blueprint_panel_id": "92384782-2757-4eeb-ac1a-94f54aea0cad",
              "rotation": 0,
              "type": "text",
              "data": {
                "text": "Authority/HUN"
              }
            },
            {
              "blueprint_panel_id": "cff4dfa2-2de8-4320-b0b1-224e85db59db",
              "rotation": 0,
              "type": "text",
              "data": {
                "text": "25"
              }
            },
            {
              "blueprint_panel_id": "7f0d98a6-7eaf-40e4-a5a1-fcd174e78941",
              "rotation": 0,
              "type": "text",
              "data": {
                "text": "25"
              }
            },
            {
              "blueprint_panel_id": "ee7f97aa-6f6c-4eea-90c9-c0263053a61c",
              "rotation": 0,
              "type": "text",
              "data": {
                "text": "50"
              }
            },
            {
              "blueprint_panel_id": "df446f32-d134-4afa-ae86-5d307f9fab6d",
              "rotation": 0,
              "type": "image",
              "data": {
                "uri": "%PROJECT%/Baro orban.jpg",
                "zoom": 1.0,
                "offset": "0.004061358, -0.1723549"
              }
            },
            {
              "blueprint_panel_id": "24205eff-c76a-4f64-b312-a2a9262be6e5",
              "rotation": 0,
              "padding": "0, 0, 0, 0",
              "type": "text",
              "data": {
                "text": "{Abstract/cycle}",
                "color": "#FF8200FF",
                "outline_length": 1.0,
                "image_offset": "0, 0"
              }
            },
            {
              "blueprint_panel_id": "f81609a7-abac-42dc-bcb4-48ac8d0e1516",
              "rotation": 0,
              "type": "text",
              "data": {
                "text": "{Abstract/plain-circle} 2",
                "color": "#FF8200FF"
              }
            },
            {
              "blueprint_panel_id": "693b769c-1e06-4eba-ab1f-f972d2473746",
              "rotation": 0,
              "type": "text",
              "data": {
                "text": "\n"
              }
            },
            {
              "blueprint_panel_id": "6a7144d4-6d17-4957-a633-c8b17b11146d",
              "rotation": 0,
              "type": "text",
              "data": {
                "text": "\n"
              }
            },
            {
              "blueprint_panel_id": "ae20974a-89fb-4b5a-976d-8fe94f1f240d",
              "rotation": 0,
              "type": "text",
              "data": {
                "text": "\n"
              }
            },
            {
              "blueprint_panel_id": "1a958a14-339a-4740-b783-a4a2e494fc2a",
              "rotation": 0,
              "type": "text",
              "data": {
                "text": "Victor {Basic/st1_star} Baron"
              }
            }
          ]
        }
      ]
    },
    {
      "card_id": "08da9596-46ab-4b4a-a3df-d1c706a0b2d7",
      "amount": 1,
      "front_layers": [
        {
          "blueprint_layer_id": "82588eae-b753-42a6-b723-200e1aebce76",
          "panels": [
            {
              "blueprint_panel_id": "655eb452-7f0a-46cd-9f92-50031ba1486a",
              "rotation": 0,
              "type": "icon",
              "data": {
                "uri": "Body&Actions/semi-closed-eye",
                "color_tint": "#FFFFFFFF",
                "color_background": "#00000000"
              }
            }
          ]
        },
        {
          "blueprint_layer_id": "fd780760-2006-4822-aac5-c6b3e1a23511",
          "panels": [
            {
              "blueprint_panel_id": "8f334754-feb9-4f34-b2a9-f4092ee70b24",
              "rotation": 0,
              "type": "text",
              "data": {
                "text": "Weapon:"
              }
            },
            {
              "blueprint_panel_id": "42ba2cce-da7d-4e9e-acca-b1c8bfe55eec",
              "rotation": 0,
              "type": "text",
              "data": {
                "text": "{Weapons/two-handed-sword}Sword"
              }
            },
            {
              "blueprint_panel_id": "60f160b7-c538-4fe8-9143-db7f1c33babc",
              "rotation": 0,
              "type": "text",
              "data": {
                "text": "<b>Scouting:</b> If you call this card {Basic/st3_playback_play} you can select a card from your <b>enemies hand</b>, you can look at that card."
              }
            },
            {
              "blueprint_panel_id": "92384782-2757-4eeb-ac1a-94f54aea0cad",
              "rotation": 0,
              "type": "text",
              "data": {
                "text": "Fighter/HUN"
              }
            },
            {
              "blueprint_panel_id": "cff4dfa2-2de8-4320-b0b1-224e85db59db",
              "rotation": 0,
              "type": "text",
              "data": {
                "text": "6"
              }
            },
            {
              "blueprint_panel_id": "7f0d98a6-7eaf-40e4-a5a1-fcd174e78941",
              "rotation": 0,
              "type": "text",
              "data": {
                "text": "15"
              }
            },
            {
              "blueprint_panel_id": "ee7f97aa-6f6c-4eea-90c9-c0263053a61c",
              "rotation": 0,
              "type": "text",
              "data": {
                "text": "40"
              }
            },
            {
              "blueprint_panel_id": "df446f32-d134-4afa-ae86-5d307f9fab6d",
              "rotation": 0,
              "type": "image",
              "data": {
                "uri": "%PROJECT%/IMG_1087.JPG",
                "zoom": 1.1,
                "offset": "-0.05244387, -0.03454657"
              }
            },
            {
              "blueprint_panel_id": "24205eff-c76a-4f64-b312-a2a9262be6e5",
              "rotation": 0,
              "padding": "0, 0, 0, 0",
              "type": "text",
              "data": {
                "text": "{Abstract/plain-circle} 2",
                "color": "#FF8200FF",
                "outline_length": 1.0,
                "image_offset": "0, 0"
              }
            },
            {
              "blueprint_panel_id": "f81609a7-abac-42dc-bcb4-48ac8d0e1516",
              "rotation": 0,
              "type": "text",
              "data": {
                "text": "\n"
              }
            },
            {
              "blueprint_panel_id": "693b769c-1e06-4eba-ab1f-f972d2473746",
              "rotation": 0,
              "type": "text",
              "data": {
                "text": "\n"
              }
            },
            {
              "blueprint_panel_id": "6a7144d4-6d17-4957-a633-c8b17b11146d",
              "rotation": 0,
              "type": "text",
              "data": {
                "text": "\n"
              }
            },
            {
              "blueprint_panel_id": "ae20974a-89fb-4b5a-976d-8fe94f1f240d",
              "rotation": 0,
              "type": "text",
              "data": {
                "text": "\n"
              }
            },
            {
              "blueprint_panel_id": "1a958a14-339a-4740-b783-a4a2e494fc2a",
              "rotation": 0,
              "type": "text",
              "data": {
                "text": "Hussar"
              }
            }
          ]
        }
      ]
    },
    {
      "card_id": "8f4d5746-79bc-4776-a777-66790e394192",
      "amount": 1,
      "front_layers": [
        {
          "blueprint_layer_id": "82588eae-b753-42a6-b723-200e1aebce76",
          "panels": [
            {
              "blueprint_panel_id": "655eb452-7f0a-46cd-9f92-50031ba1486a",
              "rotation": 0,
              "type": "icon",
              "data": {
                "uri": "Body&Actions/ages",
                "color_tint": "#FFFFFFFF",
                "color_background": "#00000000"
              }
            }
          ]
        },
        {
          "blueprint_layer_id": "fd780760-2006-4822-aac5-c6b3e1a23511",
          "panels": [
            {
              "blueprint_panel_id": "8f334754-feb9-4f34-b2a9-f4092ee70b24",
              "rotation": 0,
              "type": "text",
              "data": {
                "text": "Weapon:"
              }
            },
            {
              "blueprint_panel_id": "42ba2cce-da7d-4e9e-acca-b1c8bfe55eec",
              "rotation": 0,
              "type": "text",
              "data": {
                "text": "{Cinema/pistol-gun}Guns"
              }
            },
            {
              "blueprint_panel_id": "60f160b7-c538-4fe8-9143-db7f1c33babc",
              "rotation": 0,
              "type": "text",
              "data": {
                "text": "<i>The guardians of the nation with a proud history of courage and resilience. They stand ready to protect their land and their tradition with their modern and professional army, air force, special forces, and reserve forces.</i>"
              }
            },
            {
              "blueprint_panel_id": "92384782-2757-4eeb-ac1a-94f54aea0cad",
              "rotation": 0,
              "type": "text",
              "data": {
                "text": "Army/HUN"
              }
            },
            {
              "blueprint_panel_id": "cff4dfa2-2de8-4320-b0b1-224e85db59db",
              "rotation": 0,
              "type": "text",
              "data": {
                "text": "20"
              }
            },
            {
              "blueprint_panel_id": "7f0d98a6-7eaf-40e4-a5a1-fcd174e78941",
              "rotation": 0,
              "type": "text",
              "data": {
                "text": "13"
              }
            },
            {
              "blueprint_panel_id": "ee7f97aa-6f6c-4eea-90c9-c0263053a61c",
              "rotation": 0,
              "type": "text",
              "data": {
                "text": "25"
              }
            },
            {
              "blueprint_panel_id": "df446f32-d134-4afa-ae86-5d307f9fab6d",
              "rotation": 0,
              "type": "image",
              "data": {
                "uri": "%PROJECT%/IMG_hun.png",
                "zoom": 1.30000007,
                "offset": "0.1534385, -0.2494279"
              }
            },
            {
              "blueprint_panel_id": "24205eff-c76a-4f64-b312-a2a9262be6e5",
              "rotation": 0,
              "padding": "0, 0, 0, 0",
              "type": "text",
              "data": {
                "text": "{Abstract/plain-circle} 1",
                "color": "#FF8200FF",
                "outline_length": 1.0,
                "image_offset": "0, 0"
              }
            },
            {
              "blueprint_panel_id": "f81609a7-abac-42dc-bcb4-48ac8d0e1516",
              "rotation": 0,
              "type": "text",
              "data": {
                "text": "{Abstract/plain-circle} 1"
              }
            },
            {
              "blueprint_panel_id": "693b769c-1e06-4eba-ab1f-f972d2473746",
              "rotation": 0,
              "type": "text",
              "data": {
                "text": "\n"
              }
            },
            {
              "blueprint_panel_id": "6a7144d4-6d17-4957-a633-c8b17b11146d",
              "rotation": 0,
              "type": "text",
              "data": {
                "text": "\n"
              }
            },
            {
              "blueprint_panel_id": "ae20974a-89fb-4b5a-976d-8fe94f1f240d",
              "rotation": 0,
              "type": "text",
              "data": {
                "text": "\n"
              }
            },
            {
              "blueprint_panel_id": "1a958a14-339a-4740-b783-a4a2e494fc2a",
              "rotation": 0,
              "type": "text",
              "data": {
                "text": "Hungarian Defense Forces"
              }
            }
          ]
        }
      ]
    },
    {
      "card_id": "5f16bf17-0e4c-4659-bb48-3762c6690f19",
      "amount": 1,
      "front_layers": [
        {
          "blueprint_layer_id": "82588eae-b753-42a6-b723-200e1aebce76",
          "panels": [
            {
              "blueprint_panel_id": "655eb452-7f0a-46cd-9f92-50031ba1486a",
              "rotation": 0,
              "type": "icon",
              "data": {
                "uri": "Body&Actions/ages",
                "color_tint": "#FFFFFFFF",
                "color_background": "#00000000"
              }
            }
          ]
        },
        {
          "blueprint_layer_id": "fd780760-2006-4822-aac5-c6b3e1a23511",
          "panels": [
            {
              "blueprint_panel_id": "8f334754-feb9-4f34-b2a9-f4092ee70b24",
              "rotation": 0,
              "type": "text",
              "data": {
                "text": "Weapon:"
              }
            },
            {
              "blueprint_panel_id": "42ba2cce-da7d-4e9e-acca-b1c8bfe55eec",
              "rotation": 0,
              "type": "text",
              "data": {
                "text": "{Cinema/pistol-gun}Guns"
              }
            },
            {
              "blueprint_panel_id": "60f160b7-c538-4fe8-9143-db7f1c33babc",
              "rotation": 0,
              "type": "text",
              "data": {
                "text": "<i>A national law enforcement agency that serves under the Ministry of the Interior. It carries out various duties, such as patrolling, investigating, traffic control, and border protection.</i>"
              }
            },
            {
              "blueprint_panel_id": "92384782-2757-4eeb-ac1a-94f54aea0cad",
              "rotation": 0,
              "type": "text",
              "data": {
                "text": "Authority/HUN"
              }
            },
            {
              "blueprint_panel_id": "cff4dfa2-2de8-4320-b0b1-224e85db59db",
              "rotation": 0,
              "type": "text",
              "data": {
                "text": "10"
              }
            },
            {
              "blueprint_panel_id": "7f0d98a6-7eaf-40e4-a5a1-fcd174e78941",
              "rotation": 0,
              "type": "text",
              "data": {
                "text": "15"
              }
            },
            {
              "blueprint_panel_id": "ee7f97aa-6f6c-4eea-90c9-c0263053a61c",
              "rotation": 0,
              "type": "text",
              "data": {
                "text": "20"
              }
            },
            {
              "blueprint_panel_id": "df446f32-d134-4afa-ae86-5d307f9fab6d",
              "rotation": 0,
              "type": "image",
              "data": {
                "uri": "%PROJECT%/Magyar_Police.JPG",
                "zoom": 1.50000012,
                "offset": "-0.03065922, -0.07763936"
              }
            },
            {
              "blueprint_panel_id": "24205eff-c76a-4f64-b312-a2a9262be6e5",
              "rotation": 0,
              "padding": "0, 0, 0, 0",
              "type": "text",
              "data": {
                "text": "{Abstract/plain-circle} 1",
                "color": "#FF8200FF",
                "outline_length": 1.0,
                "image_offset": "0, 0"
              }
            },
            {
              "blueprint_panel_id": "f81609a7-abac-42dc-bcb4-48ac8d0e1516",
              "rotation": 0,
              "type": "text",
              "data": {
                "text": " "
              }
            },
            {
              "blueprint_panel_id": "693b769c-1e06-4eba-ab1f-f972d2473746",
              "rotation": 0,
              "type": "text",
              "data": {
                "text": "\n"
              }
            },
            {
              "blueprint_panel_id": "6a7144d4-6d17-4957-a633-c8b17b11146d",
              "rotation": 0,
              "type": "text",
              "data": {
                "text": "\n"
              }
            },
            {
              "blueprint_panel_id": "ae20974a-89fb-4b5a-976d-8fe94f1f240d",
              "rotation": 0,
              "type": "text",
              "data": {
                "text": "\n"
              }
            },
            {
              "blueprint_panel_id": "1a958a14-339a-4740-b783-a4a2e494fc2a",
              "rotation": 0,
              "type": "text",
              "data": {
                "text": "Hungarian Police"
              }
            }
          ]
        }
      ]
    },
    {
      "card_id": "e579ecb4-f094-4c69-8700-ae6d80478eeb",
      "amount": 1,
      "front_layers": [
        {
          "blueprint_layer_id": "71823e84-1fd7-4973-83c0-6ac3de0c0b49",
          "panels": [
            {
              "blueprint_panel_id": "414866c1-e7c1-485e-9f74-9d3312684907",
              "rotation": 0,
              "type": "image",
              "data": {
                "zoom": 1.0,
                "tint": "#3E3E3FFF"
              }
            }
          ]
        },
        {
          "blueprint_layer_id": "82588eae-b753-42a6-b723-200e1aebce76",
          "panels": [
            {
              "blueprint_panel_id": "46b21502-1507-4a7d-9df6-4f93582b618d",
              "rotation": 0
            },
            {
              "blueprint_panel_id": "655eb452-7f0a-46cd-9f92-50031ba1486a",
              "rotation": 0,
              "type": "icon",
              "data": {
                "uri": "Body&Actions/ba3_back_pain",
                "color_tint": "#FFFFFFFF",
                "color_background": "#00000000"
              }
            }
          ]
        },
        {
          "blueprint_layer_id": "fd780760-2006-4822-aac5-c6b3e1a23511",
          "panels": [
            {
              "blueprint_panel_id": "42ba2cce-da7d-4e9e-acca-b1c8bfe55eec",
              "rotation": 0,
              "type": "text",
              "data": {
                "text": "{Body&Actions/punch}\"Guns\""
              }
            },
            {
              "blueprint_panel_id": "60f160b7-c538-4fe8-9143-db7f1c33babc",
              "rotation": 0,
              "type": "text",
              "data": {
                "text": "<b>Stun</b>: Instead of attacking {Basic/st3_playback_play} You can block an <b>enemy hero</b> from attacking for one turn."
              }
            },
            {
              "blueprint_panel_id": "92384782-2757-4eeb-ac1a-94f54aea0cad",
              "rotation": 0,
              "type": "text",
              "data": {
                "text": "Fighter/BUL"
              }
            },
            {
              "blueprint_panel_id": "cff4dfa2-2de8-4320-b0b1-224e85db59db",
              "rotation": 0,
              "type": "text",
              "data": {
                "text": "6"
              }
            },
            {
              "blueprint_panel_id": "7f0d98a6-7eaf-40e4-a5a1-fcd174e78941",
              "rotation": 0,
              "type": "text",
              "data": {
                "text": "18"
              }
            },
            {
              "blueprint_panel_id": "ee7f97aa-6f6c-4eea-90c9-c0263053a61c",
              "rotation": 0,
              "type": "text",
              "data": {
                "text": "40"
              }
            },
            {
              "blueprint_panel_id": "df446f32-d134-4afa-ae86-5d307f9fab6d",
              "rotation": 0,
              "type": "image",
              "data": {
                "uri": "%PROJECT%/rosco.png",
                "offset": "-0.008962174, -0.3212307"
              }
            },
            {
              "blueprint_panel_id": "24205eff-c76a-4f64-b312-a2a9262be6e5",
              "rotation": 0,
              "type": "text",
              "data": {
                "text": "{Abstract/plain-circle}1",
                "color": "#767575FF"
              }
            },
            {
              "blueprint_panel_id": "f81609a7-abac-42dc-bcb4-48ac8d0e1516",
              "rotation": 0,
              "type": "text",
              "data": {
                "text": "{Abstract/plain-circle}1",
                "color": "#FFFFFFFF"
              }
            },
            {
              "blueprint_panel_id": "693b769c-1e06-4eba-ab1f-f972d2473746",
              "rotation": 0,
              "type": "text",
              "data": {
                "text": "\n"
              }
            },
            {
              "blueprint_panel_id": "6a7144d4-6d17-4957-a633-c8b17b11146d",
              "rotation": 0,
              "type": "text",
              "data": {
                "text": "\n"
              }
            },
            {
              "blueprint_panel_id": "ae20974a-89fb-4b5a-976d-8fe94f1f240d",
              "rotation": 0,
              "type": "text",
              "data": {
                "text": "\n"
              }
            },
            {
              "blueprint_panel_id": "1a958a14-339a-4740-b783-a4a2e494fc2a",
              "rotation": 0,
              "type": "text",
              "data": {
                "text": "Boxer"
              }
            }
          ]
        }
      ]
    },
    {
      "card_id": "59b10448-714d-433a-98f9-bac61f26246c",
      "amount": 1,
      "front_layers": [
        {
          "blueprint_layer_id": "71823e84-1fd7-4973-83c0-6ac3de0c0b49",
          "panels": [
            {
              "blueprint_panel_id": "414866c1-e7c1-485e-9f74-9d3312684907",
              "rotation": 0,
              "type": "image",
              "data": {
                "zoom": 1.0,
                "tint": "#3E3E3FFF"
              }
            }
          ]
        },
        {
          "blueprint_layer_id": "82588eae-b753-42a6-b723-200e1aebce76",
          "panels": [
            {
              "blueprint_panel_id": "46b21502-1507-4a7d-9df6-4f93582b618d",
              "rotation": 0
            },
            {
              "blueprint_panel_id": "655eb452-7f0a-46cd-9f92-50031ba1486a",
              "rotation": 0,
              "type": "icon",
              "data": {
                "uri": "Body&Actions/ba3_back_pain",
                "color_tint": "#FFFFFFFF",
                "color_background": "#00000000"
              }
            }
          ]
        },
        {
          "blueprint_layer_id": "fd780760-2006-4822-aac5-c6b3e1a23511",
          "panels": [
            {
              "blueprint_panel_id": "42ba2cce-da7d-4e9e-acca-b1c8bfe55eec",
              "rotation": 0,
              "type": "text",
              "data": {
                "text": "{Body&Actions/punch}Gloves"
              }
            },
            {
              "blueprint_panel_id": "60f160b7-c538-4fe8-9143-db7f1c33babc",
              "rotation": 0,
              "type": "text",
              "data": {
                "text": "<b>Evade</b>: When being attacked{Basic/st3_playback_play} The first attack is going to be a miss."
              }
            },
            {
              "blueprint_panel_id": "92384782-2757-4eeb-ac1a-94f54aea0cad",
              "rotation": 0,
              "type": "text",
              "data": {
                "text": "Fighter/BUL"
              }
            },
            {
              "blueprint_panel_id": "cff4dfa2-2de8-4320-b0b1-224e85db59db",
              "rotation": 0,
              "type": "text",
              "data": {
                "text": "10"
              }
            },
            {
              "blueprint_panel_id": "7f0d98a6-7eaf-40e4-a5a1-fcd174e78941",
              "rotation": 0,
              "type": "text",
              "data": {
                "text": "25"
              }
            },
            {
              "blueprint_panel_id": "ee7f97aa-6f6c-4eea-90c9-c0263053a61c",
              "rotation": 0,
              "type": "text",
              "data": {
                "text": "45"
              }
            },
            {
              "blueprint_panel_id": "df446f32-d134-4afa-ae86-5d307f9fab6d",
              "rotation": 0,
              "type": "image",
              "data": {
                "uri": "%PROJECT%/Boxer_Sp.JPG",
                "zoom": 1.1,
                "offset": "0.003797024, -0.2966895"
              }
            },
            {
              "blueprint_panel_id": "24205eff-c76a-4f64-b312-a2a9262be6e5",
              "rotation": 0,
              "type": "text",
              "data": {
                "text": "{Abstract/cycle}",
                "color": "#767575FF"
              }
            },
            {
              "blueprint_panel_id": "f81609a7-abac-42dc-bcb4-48ac8d0e1516",
              "rotation": 0,
              "type": "text",
              "data": {
                "text": "{Abstract/plain-circle}2",
                "color": "#767575FF"
              }
            },
            {
              "blueprint_panel_id": "693b769c-1e06-4eba-ab1f-f972d2473746",
              "rotation": 0,
              "type": "text",
              "data": {
                "text": "\n"
              }
            },
            {
              "blueprint_panel_id": "6a7144d4-6d17-4957-a633-c8b17b11146d",
              "rotation": 0,
              "type": "text",
              "data": {
                "text": "\n"
              }
            },
            {
              "blueprint_panel_id": "ae20974a-89fb-4b5a-976d-8fe94f1f240d",
              "rotation": 0,
              "type": "text",
              "data": {
                "text": "\n"
              }
            },
            {
              "blueprint_panel_id": "1a958a14-339a-4740-b783-a4a2e494fc2a",
              "rotation": 0,
              "type": "text",
              "data": {
                "text": "Boxer {Basic/st1_star} Combat Ready"
              }
            }
          ]
        }
      ]
    },
    {
      "card_id": "57020c22-dee0-418e-a5da-86a86e2ce530",
      "amount": 1,
      "front_layers": [
        {
          "blueprint_layer_id": "71823e84-1fd7-4973-83c0-6ac3de0c0b49",
          "panels": [
            {
              "blueprint_panel_id": "414866c1-e7c1-485e-9f74-9d3312684907",
              "type": "image",
              "data": {
                "tint": "#3E3E3FFF"
              }
            }
          ]
        },
        {
          "blueprint_layer_id": "fd780760-2006-4822-aac5-c6b3e1a23511",
          "panels": [
            {
              "blueprint_panel_id": "42ba2cce-da7d-4e9e-acca-b1c8bfe55eec",
              "type": "text",
              "data": {
                "text": "{Body&Actions/punch}None"
              }
            },
            {
              "blueprint_panel_id": "60f160b7-c538-4fe8-9143-db7f1c33babc",
              "type": "text",
              "data": {
                "text": "<b>Limited Arsenal</b>: In the strategy phase{Basic/st3_playback_play} Can only equip {Creatures/claw-hammer}Blunt weapons."
              }
            },
            {
              "blueprint_panel_id": "92384782-2757-4eeb-ac1a-94f54aea0cad",
              "type": "text",
              "data": {
                "text": "Underdog"
              }
            },
            {
              "blueprint_panel_id": "cff4dfa2-2de8-4320-b0b1-224e85db59db",
              "type": "text",
              "data": {
                "text": "5"
              }
            },
            {
              "blueprint_panel_id": "7f0d98a6-7eaf-40e4-a5a1-fcd174e78941",
              "type": "text",
              "data": {
                "text": "5"
              }
            },
            {
              "blueprint_panel_id": "ee7f97aa-6f6c-4eea-90c9-c0263053a61c",
              "type": "text",
              "data": {
                "text": "15"
              }
            },
            {
              "blueprint_panel_id": "df446f32-d134-4afa-ae86-5d307f9fab6d",
              "type": "image",
              "data": {
                "uri": "%PROJECT%/dream_TradingCard.jpg",
                "offset": "-0.003596214, -0.09156928"
              }
            },
            {
              "blueprint_panel_id": "24205eff-c76a-4f64-b312-a2a9262be6e5",
              "type": "text",
              "data": {
                "text": "{Abstract/plain-circle}1",
                "color": "#767575FF"
              }
            },
            {
              "blueprint_panel_id": "f81609a7-abac-42dc-bcb4-48ac8d0e1516",
              "type": "text",
              "data": {
                "text": " "
              }
            },
            {
              "blueprint_panel_id": "693b769c-1e06-4eba-ab1f-f972d2473746",
              "type": "text",
              "data": {
                "text": " "
              }
            },
            {
              "blueprint_panel_id": "6a7144d4-6d17-4957-a633-c8b17b11146d",
              "type": "text",
              "data": {
                "text": " "
              }
            },
            {
              "blueprint_panel_id": "1a958a14-339a-4740-b783-a4a2e494fc2a",
              "type": "text",
              "data": {
                "text": "Gipsy Kids"
              }
            }
          ]
        }
      ]
    },
    {
      "card_id": "26e8b9bd-4977-4cb3-94e5-8f4b2429e86b",
      "amount": 1,
      "front_layers": [
        {
          "blueprint_layer_id": "71823e84-1fd7-4973-83c0-6ac3de0c0b49",
          "panels": [
            {
              "blueprint_panel_id": "414866c1-e7c1-485e-9f74-9d3312684907",
              "rotation": 0,
              "type": "image",
              "data": {
                "tint": "#3E3E3FFF"
              }
            }
          ]
        },
        {
          "blueprint_layer_id": "82588eae-b753-42a6-b723-200e1aebce76",
          "panels": [
            {
              "blueprint_panel_id": "655eb452-7f0a-46cd-9f92-50031ba1486a",
              "rotation": 0,
              "type": "icon",
              "data": {
                "uri": "Body&Actions/ages",
                "color_tint": "#FFFFFFFF",
                "color_background": "#00000000"
              }
            }
          ]
        },
        {
          "blueprint_layer_id": "fd780760-2006-4822-aac5-c6b3e1a23511",
          "panels": [
            {
              "blueprint_panel_id": "8f334754-feb9-4f34-b2a9-f4092ee70b24",
              "rotation": 0,
              "type": "text",
              "data": {
                "text": "Weapon:"
              }
            },
            {
              "blueprint_panel_id": "42ba2cce-da7d-4e9e-acca-b1c8bfe55eec",
              "rotation": 0,
              "type": "text",
              "data": {
                "text": "{Body&Actions/punch}None"
              }
            },
            {
              "blueprint_panel_id": "60f160b7-c538-4fe8-9143-db7f1c33babc",
              "rotation": 0,
              "type": "text",
              "data": {
                "text": "<b>Combo</b>: if you call this card{Basic/st3_playback_play} Every attack on a RUS and CHN Herocarsa gets redirected at this card."
              }
            },
            {
              "blueprint_panel_id": "92384782-2757-4eeb-ac1a-94f54aea0cad",
              "rotation": 0,
              "type": "text",
              "data": {
                "text": "Undrdog/HUN"
              }
            },
            {
              "blueprint_panel_id": "cff4dfa2-2de8-4320-b0b1-224e85db59db",
              "rotation": 0,
              "type": "text",
              "data": {
                "text": "20"
              }
            },
            {
              "blueprint_panel_id": "7f0d98a6-7eaf-40e4-a5a1-fcd174e78941",
              "rotation": 0,
              "type": "text",
              "data": {
                "text": "13"
              }
            },
            {
              "blueprint_panel_id": "ee7f97aa-6f6c-4eea-90c9-c0263053a61c",
              "rotation": 0,
              "type": "text",
              "data": {
                "text": "25"
              }
            },
            {
              "blueprint_panel_id": "df446f32-d134-4afa-ae86-5d307f9fab6d",
              "rotation": 0,
              "type": "image",
              "data": {
                "uri": "%PROJECT%/MC_Isti.jpg",
                "zoom": 1.1,
                "offset": "-0.03615537, -0.3553076"
              }
            },
            {
              "blueprint_panel_id": "24205eff-c76a-4f64-b312-a2a9262be6e5",
              "rotation": 0,
              "padding": "0, 0, 0, 0",
              "type": "text",
              "data": {
                "text": "{Abstract/plain-circle} 1",
                "color": "#767575FF",
                "outline_length": 1.0,
                "image_offset": "0, 0"
              }
            },
            {
              "blueprint_panel_id": "f81609a7-abac-42dc-bcb4-48ac8d0e1516",
              "rotation": 0,
              "type": "text",
              "data": {
                "text": "{Abstract/plain-circle} 1",
                "color": "#FFFFFFFF"
              }
            },
            {
              "blueprint_panel_id": "693b769c-1e06-4eba-ab1f-f972d2473746",
              "rotation": 0,
              "type": "text",
              "data": {
                "text": "\n"
              }
            },
            {
              "blueprint_panel_id": "6a7144d4-6d17-4957-a633-c8b17b11146d",
              "rotation": 0,
              "type": "text",
              "data": {
                "text": "\n"
              }
            },
            {
              "blueprint_panel_id": "1a958a14-339a-4740-b783-a4a2e494fc2a",
              "rotation": 0,
              "type": "text",
              "data": {
                "text": " Steve Macman"
              }
            }
          ]
        }
      ]
    },
    {
      "card_id": "3b64a3a4-b1fd-4483-b7f8-a873bcc4da12",
      "amount": 1,
      "front_layers": [
        {
          "blueprint_layer_id": "71823e84-1fd7-4973-83c0-6ac3de0c0b49",
          "panels": [
            {
              "blueprint_panel_id": "414866c1-e7c1-485e-9f74-9d3312684907",
              "rotation": 0,
              "type": "image",
              "data": {
                "zoom": 1.0,
                "tint": "#3E3E3FFF"
              }
            }
          ]
        },
        {
          "blueprint_layer_id": "82588eae-b753-42a6-b723-200e1aebce76",
          "panels": [
            {
              "blueprint_panel_id": "46b21502-1507-4a7d-9df6-4f93582b618d",
              "rotation": 0
            },
            {
              "blueprint_panel_id": "655eb452-7f0a-46cd-9f92-50031ba1486a",
              "rotation": 0,
              "type": "icon",
              "data": {
                "uri": "Body&Actions/ba3_back_pain",
                "color_tint": "#FFFFFFFF",
                "color_background": "#00000000"
              }
            }
          ]
        },
        {
          "blueprint_layer_id": "fd780760-2006-4822-aac5-c6b3e1a23511",
          "panels": [
            {
              "blueprint_panel_id": "42ba2cce-da7d-4e9e-acca-b1c8bfe55eec",
              "rotation": 0,
              "type": "text",
              "data": {
                "text": "{Weapons/two-handed-sword}Katana "
              }
            },
            {
              "blueprint_panel_id": "60f160b7-c538-4fe8-9143-db7f1c33babc",
              "rotation": 0,
              "type": "text",
              "data": {
                "text": "<b>Call Family</b>: If this card is defeated {Basic/st3_playback_play} Put <b>one Black mana</b> from the field into your graveyard then summon a <b>Szamu Raj</b> from your deck."
              }
            },
            {
              "blueprint_panel_id": "92384782-2757-4eeb-ac1a-94f54aea0cad",
              "rotation": 0,
              "type": "text",
              "data": {
                "text": "Underdog"
              }
            },
            {
              "blueprint_panel_id": "cff4dfa2-2de8-4320-b0b1-224e85db59db",
              "rotation": 0,
              "type": "text",
              "data": {
                "text": "0"
              }
            },
            {
              "blueprint_panel_id": "7f0d98a6-7eaf-40e4-a5a1-fcd174e78941",
              "rotation": 0,
              "type": "text",
              "data": {
                "text": "10"
              }
            },
            {
              "blueprint_panel_id": "ee7f97aa-6f6c-4eea-90c9-c0263053a61c",
              "rotation": 0,
              "type": "text",
              "data": {
                "text": "15"
              }
            },
            {
              "blueprint_panel_id": "df446f32-d134-4afa-ae86-5d307f9fab6d",
              "rotation": 0,
              "type": "image",
              "data": {
                "uri": "%PROJECT%/Comic_Szamu RAJ.jpg",
                "offset": "0.0027429, -0.2484944"
              }
            },
            {
              "blueprint_panel_id": "24205eff-c76a-4f64-b312-a2a9262be6e5",
              "rotation": 0,
              "type": "text",
              "data": {
                "text": "{Abstract/plain-circle}1",
                "color": "#767575FF"
              }
            },
            {
              "blueprint_panel_id": "f81609a7-abac-42dc-bcb4-48ac8d0e1516",
              "enabled": false,
              "rotation": 0,
              "type": "text",
              "data": {
                "text": "{Abstract/plain-circle}1",
                "color": "#767575FF"
              }
            },
            {
              "blueprint_panel_id": "693b769c-1e06-4eba-ab1f-f972d2473746",
              "rotation": 0,
              "type": "text",
              "data": {
                "text": "\n"
              }
            },
            {
              "blueprint_panel_id": "6a7144d4-6d17-4957-a633-c8b17b11146d",
              "rotation": 0,
              "type": "text",
              "data": {
                "text": "\n"
              }
            },
            {
              "blueprint_panel_id": "1a958a14-339a-4740-b783-a4a2e494fc2a",
              "rotation": 0,
              "type": "text",
              "data": {
                "text": "Szamu Raj"
              }
            }
          ]
        }
      ]
    },
    {
      "card_id": "e168f82f-b426-4c79-aecc-c947ad5d539d",
      "amount": 1,
      "front_layers": [
        {
          "blueprint_layer_id": "71823e84-1fd7-4973-83c0-6ac3de0c0b49",
          "panels": [
            {
              "blueprint_panel_id": "414866c1-e7c1-485e-9f74-9d3312684907",
              "rotation": 0,
              "type": "image",
              "data": {
                "tint": "#AD0D00FF"
              }
            }
          ]
        },
        {
          "blueprint_layer_id": "82588eae-b753-42a6-b723-200e1aebce76",
          "panels": [
            {
              "blueprint_panel_id": "655eb452-7f0a-46cd-9f92-50031ba1486a",
              "rotation": 0,
              "type": "icon",
              "data": {
                "uri": "Body&Actions/ages",
                "color_tint": "#FFFFFFFF",
                "color_background": "#00000000"
              }
            }
          ]
        },
        {
          "blueprint_layer_id": "fd780760-2006-4822-aac5-c6b3e1a23511",
          "panels": [
            {
              "blueprint_panel_id": "8f334754-feb9-4f34-b2a9-f4092ee70b24",
              "rotation": 0,
              "type": "text",
              "data": {
                "text": "Weapon:"
              }
            },
            {
              "blueprint_panel_id": "42ba2cce-da7d-4e9e-acca-b1c8bfe55eec",
              "rotation": 0,
              "type": "text",
              "data": {
                "text": "{Cinema/pistol-gun}Guns"
              }
            },
            {
              "blueprint_panel_id": "60f160b7-c538-4fe8-9143-db7f1c33babc",
              "rotation": 0,
              "type": "text",
              "data": {
                "text": "<b>Arsenal:</b> In the strategy phase {Basic/st3_playback_play} This card can equip {Creatures/claw-hammer}<b>Blunt</b> and {Cinema/pistol-gun}<b>Ranged</b> weapons."
              }
            },
            {
              "blueprint_panel_id": "92384782-2757-4eeb-ac1a-94f54aea0cad",
              "rotation": 0,
              "type": "text",
              "data": {
                "text": "Authority/GER"
              }
            },
            {
              "blueprint_panel_id": "cff4dfa2-2de8-4320-b0b1-224e85db59db",
              "rotation": 0,
              "type": "text",
              "data": {
                "text": "4"
              }
            },
            {
              "blueprint_panel_id": "7f0d98a6-7eaf-40e4-a5a1-fcd174e78941",
              "rotation": 0,
              "type": "text",
              "data": {
                "text": "12"
              }
            },
            {
              "blueprint_panel_id": "ee7f97aa-6f6c-4eea-90c9-c0263053a61c",
              "rotation": 0,
              "type": "text",
              "data": {
                "text": "20"
              }
            },
            {
              "blueprint_panel_id": "df446f32-d134-4afa-ae86-5d307f9fab6d",
              "rotation": 0,
              "type": "image",
              "data": {
                "uri": "%PROJECT%/Bundespolizei.jpg",
                "zoom": 1.1,
                "offset": "0.04748902, -0.4400114"
              }
            },
            {
              "blueprint_panel_id": "24205eff-c76a-4f64-b312-a2a9262be6e5",
              "rotation": 0,
              "padding": "0, 0, 0, 0",
              "type": "text",
              "data": {
                "text": "{Abstract/plain-circle} 1",
                "color": "#AD0D00FF",
                "outline_length": 1.0,
                "image_offset": "0, 0"
              }
            },
            {
              "blueprint_panel_id": "f81609a7-abac-42dc-bcb4-48ac8d0e1516",
              "rotation": 0,
              "type": "text",
              "data": {
                "text": " "
              }
            },
            {
              "blueprint_panel_id": "693b769c-1e06-4eba-ab1f-f972d2473746",
              "rotation": 0,
              "type": "text",
              "data": {
                "text": "\n"
              }
            },
            {
              "blueprint_panel_id": "6a7144d4-6d17-4957-a633-c8b17b11146d",
              "rotation": 0,
              "type": "text",
              "data": {
                "text": "\n"
              }
            },
            {
              "blueprint_panel_id": "ae20974a-89fb-4b5a-976d-8fe94f1f240d",
              "rotation": 0,
              "type": "text",
              "data": {
                "text": "\n"
              }
            },
            {
              "blueprint_panel_id": "1a958a14-339a-4740-b783-a4a2e494fc2a",
              "rotation": 0,
              "type": "text",
              "data": {
                "text": "Bundespolizei"
              }
            }
          ]
        }
      ]
    },
    {
      "card_id": "78b38178-da9b-40b6-a25a-5bbcefbda993",
      "amount": 1,
      "front_layers": [
        {
          "blueprint_layer_id": "71823e84-1fd7-4973-83c0-6ac3de0c0b49",
          "panels": [
            {
              "blueprint_panel_id": "414866c1-e7c1-485e-9f74-9d3312684907",
              "rotation": 0,
              "type": "image",
              "data": {
                "tint": "#AD0D00FF"
              }
            }
          ]
        },
        {
          "blueprint_layer_id": "82588eae-b753-42a6-b723-200e1aebce76",
          "panels": [
            {
              "blueprint_panel_id": "655eb452-7f0a-46cd-9f92-50031ba1486a",
              "rotation": 0,
              "type": "icon",
              "data": {
                "uri": "Other/concentration-orb",
                "color_tint": "#FFFFFFFF",
                "color_background": "#00000000"
              }
            }
          ]
        },
        {
          "blueprint_layer_id": "fd780760-2006-4822-aac5-c6b3e1a23511",
          "panels": [
            {
              "blueprint_panel_id": "42ba2cce-da7d-4e9e-acca-b1c8bfe55eec",
              "rotation": 0,
              "type": "text",
              "data": {
                "text": "{Body&Actions/punch}None"
              }
            },
            {
              "blueprint_panel_id": "60f160b7-c538-4fe8-9143-db7f1c33babc",
              "rotation": 0,
              "type": "text",
              "data": {
                "text": "<b>Sleeping</b>: If this card didn't attack last turn {Abstract/play-button} You can either \n{Abstract/plain-circle}  Recover <b>2 HP</b> for this card\n {Abstract/plain-circle} Sacrifice this card and add \n      one <b>red mana</b> to your field"
              }
            },
            {
              "blueprint_panel_id": "92384782-2757-4eeb-ac1a-94f54aea0cad",
              "rotation": 0,
              "type": "text",
              "data": {
                "text": "Snoozer/BRA"
              }
            },
            {
              "blueprint_panel_id": "cff4dfa2-2de8-4320-b0b1-224e85db59db",
              "rotation": 0,
              "type": "text",
              "data": {
                "text": "10"
              }
            },
            {
              "blueprint_panel_id": "7f0d98a6-7eaf-40e4-a5a1-fcd174e78941",
              "rotation": 0,
              "type": "text",
              "data": {
                "text": "5"
              }
            },
            {
              "blueprint_panel_id": "ee7f97aa-6f6c-4eea-90c9-c0263053a61c",
              "rotation": 0,
              "type": "text",
              "data": {
                "text": "15"
              }
            },
            {
              "blueprint_panel_id": "df446f32-d134-4afa-ae86-5d307f9fab6d",
              "rotation": 0,
              "type": "image",
              "data": {
                "uri": "%PROJECT%/Brazil.jpg",
                "zoom": 1.30000007,
                "offset": "0.04561813, -0.2388165"
              }
            },
            {
              "blueprint_panel_id": "24205eff-c76a-4f64-b312-a2a9262be6e5",
              "rotation": 0,
              "type": "text",
              "data": {
                "text": "{Abstract/plain-circle}1",
                "color": "#AD0D00FF"
              }
            },
            {
              "blueprint_panel_id": "f81609a7-abac-42dc-bcb4-48ac8d0e1516",
              "rotation": 0,
              "type": "text",
              "data": {
                "text": "{Abstract/plain-circle}1"
              }
            },
            {
              "blueprint_panel_id": "693b769c-1e06-4eba-ab1f-f972d2473746",
              "rotation": 0,
              "type": "text",
              "data": {
                "text": "\n"
              }
            },
            {
              "blueprint_panel_id": "6a7144d4-6d17-4957-a633-c8b17b11146d",
              "rotation": 0,
              "type": "text",
              "data": {
                "text": "\n"
              }
            },
            {
              "blueprint_panel_id": "ae20974a-89fb-4b5a-976d-8fe94f1f240d",
              "rotation": 0,
              "type": "text",
              "data": {
                "text": "\n"
              }
            },
            {
              "blueprint_panel_id": "1a958a14-339a-4740-b783-a4a2e494fc2a",
              "rotation": 0,
              "type": "text",
              "data": {
                "text": "Brazil X"
              }
            }
          ]
        }
      ]
    },
    {
      "card_id": "4e6f7f82-1245-4b8b-81d4-e94b2ae6bf27",
      "amount": 1,
      "front_layers": [
        {
          "blueprint_layer_id": "71823e84-1fd7-4973-83c0-6ac3de0c0b49",
          "panels": [
            {
              "blueprint_panel_id": "414866c1-e7c1-485e-9f74-9d3312684907",
              "rotation": 0,
              "type": "image",
              "data": {
                "tint": "#AD0D00FF"
              }
            }
          ]
        },
        {
          "blueprint_layer_id": "82588eae-b753-42a6-b723-200e1aebce76",
          "panels": [
            {
              "blueprint_panel_id": "655eb452-7f0a-46cd-9f92-50031ba1486a",
              "rotation": 0,
              "type": "icon",
              "data": {
                "uri": "Other/concentration-orb",
                "color_tint": "#FFFFFFFF",
                "color_background": "#00000000"
              }
            }
          ]
        },
        {
          "blueprint_layer_id": "fd780760-2006-4822-aac5-c6b3e1a23511",
          "panels": [
            {
              "blueprint_panel_id": "42ba2cce-da7d-4e9e-acca-b1c8bfe55eec",
              "rotation": 0,
              "type": "text",
              "data": {
                "text": "{Body&Actions/punch}None"
              }
            },
            {
              "blueprint_panel_id": "60f160b7-c538-4fe8-9143-db7f1c33babc",
              "rotation": 0,
              "type": "text",
              "data": {
                "text": "<b>Breaking Bank</b>: If you call this hero {Abstract/play-button} add <b>one red</b> to your hand."
              }
            },
            {
              "blueprint_panel_id": "92384782-2757-4eeb-ac1a-94f54aea0cad",
              "rotation": 0,
              "type": "text",
              "data": {
                "text": "Authority"
              }
            },
            {
              "blueprint_panel_id": "cff4dfa2-2de8-4320-b0b1-224e85db59db",
              "rotation": 0,
              "type": "text",
              "data": {
                "text": "20"
              }
            },
            {
              "blueprint_panel_id": "7f0d98a6-7eaf-40e4-a5a1-fcd174e78941",
              "rotation": 0,
              "type": "text",
              "data": {
                "text": "20"
              }
            },
            {
              "blueprint_panel_id": "ee7f97aa-6f6c-4eea-90c9-c0263053a61c",
              "rotation": 0,
              "type": "text",
              "data": {
                "text": "35"
              }
            },
            {
              "blueprint_panel_id": "df446f32-d134-4afa-ae86-5d307f9fab6d",
              "rotation": 0,
              "type": "image",
              "data": {
                "uri": "%PROJECT%/Darth soros 2.jpg",
                "zoom": 1.1,
                "offset": "-0.02000096, -0.3426448"
              }
            },
            {
              "blueprint_panel_id": "24205eff-c76a-4f64-b312-a2a9262be6e5",
              "rotation": 0,
              "type": "text",
              "data": {
                "text": "{Abstract/plain-circle}4",
                "color": "#AD0D00FF"
              }
            },
            {
              "blueprint_panel_id": "f81609a7-abac-42dc-bcb4-48ac8d0e1516",
              "rotation": 0,
              "type": "text",
              "data": {
                "text": " "
              }
            },
            {
              "blueprint_panel_id": "693b769c-1e06-4eba-ab1f-f972d2473746",
              "rotation": 0,
              "type": "text",
              "data": {
                "text": "\n"
              }
            },
            {
              "blueprint_panel_id": "6a7144d4-6d17-4957-a633-c8b17b11146d",
              "rotation": 0,
              "type": "text",
              "data": {
                "text": "\n"
              }
            },
            {
              "blueprint_panel_id": "ae20974a-89fb-4b5a-976d-8fe94f1f240d",
              "rotation": 0,
              "type": "text",
              "data": {
                "text": "\n"
              }
            },
            {
              "blueprint_panel_id": "1a958a14-339a-4740-b783-a4a2e494fc2a",
              "rotation": 0,
              "type": "text",
              "data": {
                "text": "<i>Darth</i> - Jore Sores"
              }
            }
          ]
        }
      ]
    },
    {
      "card_id": "dd412755-486d-4ac6-87ec-9729ec3d35ba",
      "amount": 1,
      "front_layers": [
        {
          "blueprint_layer_id": "71823e84-1fd7-4973-83c0-6ac3de0c0b49",
          "panels": [
            {
              "blueprint_panel_id": "414866c1-e7c1-485e-9f74-9d3312684907",
              "rotation": 0,
              "type": "image",
              "data": {
                "tint": "#AD0D00FF"
              }
            }
          ]
        },
        {
          "blueprint_layer_id": "82588eae-b753-42a6-b723-200e1aebce76",
          "panels": [
            {
              "blueprint_panel_id": "655eb452-7f0a-46cd-9f92-50031ba1486a",
              "rotation": 0,
              "type": "icon",
              "data": {
                "uri": "Other/concentration-orb",
                "color_tint": "#FFFFFFFF",
                "color_background": "#00000000"
              }
            }
          ]
        },
        {
          "blueprint_layer_id": "fd780760-2006-4822-aac5-c6b3e1a23511",
          "panels": [
            {
              "blueprint_panel_id": "42ba2cce-da7d-4e9e-acca-b1c8bfe55eec",
              "rotation": 0,
              "type": "text",
              "data": {
                "text": "{Body&Actions/punch}None"
              }
            },
            {
              "blueprint_panel_id": "60f160b7-c538-4fe8-9143-db7f1c33babc",
              "rotation": 0,
              "type": "text",
              "data": {
                "text": "<b>Breaking Bank</b>: If you call this hero {Abstract/play-button} add <b>one red</b> to your hand."
              }
            },
            {
              "blueprint_panel_id": "92384782-2757-4eeb-ac1a-94f54aea0cad",
              "rotation": 0,
              "type": "text",
              "data": {
                "text": "Authority"
              }
            },
            {
              "blueprint_panel_id": "cff4dfa2-2de8-4320-b0b1-224e85db59db",
              "rotation": 0,
              "type": "text",
              "data": {
                "text": "32"
              }
            },
            {
              "blueprint_panel_id": "7f0d98a6-7eaf-40e4-a5a1-fcd174e78941",
              "rotation": 0,
              "type": "text",
              "data": {
                "text": "7"
              }
            },
            {
              "blueprint_panel_id": "ee7f97aa-6f6c-4eea-90c9-c0263053a61c",
              "rotation": 0,
              "type": "text",
              "data": {
                "text": "30"
              }
            },
            {
              "blueprint_panel_id": "df446f32-d134-4afa-ae86-5d307f9fab6d",
              "rotation": 0,
              "type": "image",
              "data": {
                "uri": "%PROJECT%/soros.jpg",
                "zoom": 1.30000007,
                "offset": "-0.01088721, -0.4823409"
              }
            },
            {
              "blueprint_panel_id": "24205eff-c76a-4f64-b312-a2a9262be6e5",
              "rotation": 0,
              "type": "text",
              "data": {
                "text": "{Abstract/plain-circle}2",
                "color": "#AD0D00FF"
              }
            },
            {
              "blueprint_panel_id": "f81609a7-abac-42dc-bcb4-48ac8d0e1516",
              "rotation": 0,
              "type": "text",
              "data": {
                "text": "{Abstract/plain-circle}1"
              }
            },
            {
              "blueprint_panel_id": "693b769c-1e06-4eba-ab1f-f972d2473746",
              "rotation": 0,
              "type": "text",
              "data": {
                "text": "\n"
              }
            },
            {
              "blueprint_panel_id": "6a7144d4-6d17-4957-a633-c8b17b11146d",
              "rotation": 0,
              "type": "text",
              "data": {
                "text": "\n"
              }
            },
            {
              "blueprint_panel_id": "ae20974a-89fb-4b5a-976d-8fe94f1f240d",
              "rotation": 0,
              "type": "text",
              "data": {
                "text": "\n"
              }
            },
            {
              "blueprint_panel_id": "1a958a14-339a-4740-b783-a4a2e494fc2a",
              "rotation": 0,
              "type": "text",
              "data": {
                "text": "Jore Sores"
              }
            }
          ]
        }
      ]
    },
    {
      "card_id": "4f35caca-8725-4583-a0af-fad1653e7d96",
      "amount": 1,
      "front_layers": [
        {
          "blueprint_layer_id": "71823e84-1fd7-4973-83c0-6ac3de0c0b49",
          "panels": [
            {
              "blueprint_panel_id": "414866c1-e7c1-485e-9f74-9d3312684907",
              "rotation": 0,
              "type": "image",
              "data": {
                "tint": "#AD0D00FF"
              }
            }
          ]
        },
        {
          "blueprint_layer_id": "82588eae-b753-42a6-b723-200e1aebce76",
          "panels": [
            {
              "blueprint_panel_id": "655eb452-7f0a-46cd-9f92-50031ba1486a",
              "rotation": 0,
              "type": "icon",
              "data": {
                "uri": "Other/concentration-orb",
                "color_tint": "#FFFFFFFF",
                "color_background": "#00000000"
              }
            }
          ]
        },
        {
          "blueprint_layer_id": "fd780760-2006-4822-aac5-c6b3e1a23511",
          "panels": [
            {
              "blueprint_panel_id": "42ba2cce-da7d-4e9e-acca-b1c8bfe55eec",
              "rotation": 0,
              "type": "text",
              "data": {
                "text": "{Weapons/two-handed-sword}{Weapons/two-handed-sword}Dual Lightsaber"
              }
            },
            {
              "blueprint_panel_id": "60f160b7-c538-4fe8-9143-db7f1c33babc",
              "rotation": 0,
              "type": "text",
              "data": {
                "text": "<b>The Force</b>: you can use 3 red mana {Abstract/play-button} You can send one <b>enemy Hero</b> card back to their hand."
              }
            },
            {
              "blueprint_panel_id": "92384782-2757-4eeb-ac1a-94f54aea0cad",
              "rotation": 0,
              "type": "text",
              "data": {
                "text": "Authority"
              }
            },
            {
              "blueprint_panel_id": "cff4dfa2-2de8-4320-b0b1-224e85db59db",
              "rotation": 0,
              "type": "text",
              "data": {
                "text": "20"
              }
            },
            {
              "blueprint_panel_id": "7f0d98a6-7eaf-40e4-a5a1-fcd174e78941",
              "rotation": 0,
              "type": "text",
              "data": {
                "text": "35"
              }
            },
            {
              "blueprint_panel_id": "ee7f97aa-6f6c-4eea-90c9-c0263053a61c",
              "rotation": 0,
              "type": "text",
              "data": {
                "text": "65"
              }
            },
            {
              "blueprint_panel_id": "df446f32-d134-4afa-ae86-5d307f9fab6d",
              "rotation": 0,
              "type": "image",
              "data": {
                "uri": "%PROJECT%/Darth soros.jpg",
                "zoom": 1.1,
                "offset": "-0.01088723, -0.2051286"
              }
            },
            {
              "blueprint_panel_id": "24205eff-c76a-4f64-b312-a2a9262be6e5",
              "rotation": 0,
              "type": "text",
              "data": {
                "text": "{Abstract/cycle}",
                "color": "#AD0D00FF"
              }
            },
            {
              "blueprint_panel_id": "f81609a7-abac-42dc-bcb4-48ac8d0e1516",
              "rotation": 0,
              "type": "text",
              "data": {
                "text": "{Abstract/plain-circle}5",
                "color": "#AD0D00FF"
              }
            },
            {
              "blueprint_panel_id": "693b769c-1e06-4eba-ab1f-f972d2473746",
              "rotation": 0,
              "type": "text",
              "data": {
                "text": " "
              }
            },
            {
              "blueprint_panel_id": "6a7144d4-6d17-4957-a633-c8b17b11146d",
              "rotation": 0,
              "type": "text",
              "data": {
                "text": "\n"
              }
            },
            {
              "blueprint_panel_id": "ae20974a-89fb-4b5a-976d-8fe94f1f240d",
              "rotation": 0,
              "type": "text",
              "data": {
                "text": "\n"
              }
            },
            {
              "blueprint_panel_id": "1a958a14-339a-4740-b783-a4a2e494fc2a",
              "rotation": 0,
              "type": "text",
              "data": {
                "text": "  Jore Sores {Abstract/round-star} Emperor "
              }
            }
          ]
        }
      ]
    },
    {
      "card_id": "7c2642fd-0d1f-42aa-a68a-b9b4b3256bc7",
      "amount": 1,
      "front_layers": [
        {
          "blueprint_layer_id": "71823e84-1fd7-4973-83c0-6ac3de0c0b49",
          "panels": [
            {
              "blueprint_panel_id": "414866c1-e7c1-485e-9f74-9d3312684907",
              "rotation": 0,
              "type": "image",
              "data": {
                "tint": "#254776FF"
              }
            }
          ]
        },
        {
          "blueprint_layer_id": "82588eae-b753-42a6-b723-200e1aebce76",
          "panels": [
            {
              "blueprint_panel_id": "655eb452-7f0a-46cd-9f92-50031ba1486a",
              "rotation": 0,
              "type": "icon",
              "data": {
                "uri": "Body&Actions/ages",
                "color_tint": "#FFFFFFFF",
                "color_background": "#00000000"
              }
            }
          ]
        },
        {
          "blueprint_layer_id": "fd780760-2006-4822-aac5-c6b3e1a23511",
          "panels": [
            {
              "blueprint_panel_id": "8f334754-feb9-4f34-b2a9-f4092ee70b24",
              "rotation": 0,
              "type": "text",
              "data": {
                "text": "Weapon:"
              }
            },
            {
              "blueprint_panel_id": "42ba2cce-da7d-4e9e-acca-b1c8bfe55eec",
              "rotation": 0,
              "type": "text",
              "data": {
                "text": "{Cinema/pistol-gun}Pistol"
              }
            },
            {
              "blueprint_panel_id": "60f160b7-c538-4fe8-9143-db7f1c33babc",
              "rotation": 0,
              "type": "text",
              "data": {
                "text": "<b>Evasedrop:</b> You can use 2 blue mana {Basic/st3_playback_play} You can look at the top three cards of the enemy's deck, then rearrange them."
              }
            },
            {
              "blueprint_panel_id": "92384782-2757-4eeb-ac1a-94f54aea0cad",
              "rotation": 0,
              "type": "text",
              "data": {
                "text": "Authority/RUS"
              }
            },
            {
              "blueprint_panel_id": "cff4dfa2-2de8-4320-b0b1-224e85db59db",
              "rotation": 0,
              "type": "text",
              "data": {
                "text": "20"
              }
            },
            {
              "blueprint_panel_id": "7f0d98a6-7eaf-40e4-a5a1-fcd174e78941",
              "rotation": 0,
              "type": "text",
              "data": {
                "text": "26"
              }
            },
            {
              "blueprint_panel_id": "ee7f97aa-6f6c-4eea-90c9-c0263053a61c",
              "rotation": 0,
              "type": "text",
              "data": {
                "text": "30"
              }
            },
            {
              "blueprint_panel_id": "df446f32-d134-4afa-ae86-5d307f9fab6d",
              "rotation": 0,
              "type": "image",
              "data": {
                "uri": "%PROJECT%/Agent Putin.JPG",
                "zoom": 1.0,
                "offset": "0.001920317, -0.3890412"
              }
            },
            {
              "blueprint_panel_id": "24205eff-c76a-4f64-b312-a2a9262be6e5",
              "rotation": 0,
              "padding": "0, 0, 0, 0",
              "type": "text",
              "data": {
                "text": "{Abstract/plain-circle} 3",
                "color": "#254776FF",
                "outline_length": 1.0,
                "image_offset": "0, 0"
              }
            },
            {
              "blueprint_panel_id": "f81609a7-abac-42dc-bcb4-48ac8d0e1516",
              "rotation": 0,
              "type": "text",
              "data": {
                "text": " "
              }
            },
            {
              "blueprint_panel_id": "693b769c-1e06-4eba-ab1f-f972d2473746",
              "rotation": 0,
              "type": "text",
              "data": {
                "text": "\n"
              }
            },
            {
              "blueprint_panel_id": "6a7144d4-6d17-4957-a633-c8b17b11146d",
              "rotation": 0,
              "type": "text",
              "data": {
                "text": "\n"
              }
            },
            {
              "blueprint_panel_id": "ae20974a-89fb-4b5a-976d-8fe94f1f240d",
              "rotation": 0,
              "type": "text",
              "data": {
                "text": "\n"
              }
            },
            {
              "blueprint_panel_id": "1a958a14-339a-4740-b783-a4a2e494fc2a",
              "rotation": 0,
              "type": "text",
              "data": {
                "text": "<i>Agent</i> - Vlad"
              }
            }
          ]
        }
      ]
    }
  ]
}